openinference/instrumentation/dspy/__init__.py
openinference/instrumentation/dspy/package.py
openinference/instrumentation/dspy/py.typed
openinference/instrumentation/dspy/version.py
clank_so_openinference_instrumentation_dspy-0.1.10.dist-info/METADATA
clank_so_openinference_instrumentation_dspy-0.1.10.dist-info/WHEEL
clank_so_openinference_instrumentation_dspy-0.1.10.dist-info/licenses/LICENSE
clank_so_openinference_instrumentation_dspy-0.1.10.dist-info/RECORD
